optihood/__init__.py
optihood/_helpers.py
optihood/buildings.py
optihood/combined_prod.py
optihood/constraints.py
optihood/converters.py
optihood/energy_network.py
optihood/entities.py
optihood/genericstorage_pit.py
optihood/labelDict.py
optihood/links.py
optihood/plot_functions.py
optihood/plot_sankey.py
optihood/py.typed
optihood/sinks.py
optihood/sources.py
optihood/storages.py
optihood/IO/__init__.py
optihood/IO/groupScenarioWriter.py
optihood/IO/individualScenarioWriter.py
optihood/IO/readers.py
optihood/IO/writers.py
optihood/MPC/__init__.py
optihood/MPC/interface.py
optihood/Visualizer/__init__.py
optihood/Visualizer/convert_scenario.py
optihood/Visualizer/scenario_to_visualizer.py
optihood/Visualizer/visualizer_app.py
optihood-0.2.4.dist-info/licenses/LICENSE
tests/__init__.py
tests/test_energy_network.py
tests/xls_helpers.py
tests/IO/__init__.py
tests/IO/test_readers.py
tests/MPC/__init__.py
tests/MPC/test_mpc.py
tests/Visualizer/__init__.py
tests/Visualizer/test_scenario_to_visualizer.py
tests/Visualizer/test_visualize_energy_network.py
optihood-0.2.4.dist-info/METADATA
optihood-0.2.4.dist-info/WHEEL
optihood-0.2.4.dist-info/top_level.txt
optihood-0.2.4.dist-info/RECORD
