Metadata-Version: 2.4
Name: optihood
Version: 0.2.4
Summary: optihood optimization framework
Home-page: https://optihood.readthedocs.io
Author: Institute for Solar Technology (SPF), OST Rapperswil
Author-email: neha.dimri@ost.ch
Classifier: Programming Language :: Python :: 3
Classifier: License :: OSI Approved :: GNU General Public License v3 or later (GPLv3+)
Classifier: Operating System :: Microsoft :: Windows
Requires-Python: >=3.12
License-File: LICENSE
Requires-Dist: bokeh
Requires-Dist: configparser
Requires-Dist: python-dateutil
Requires-Dist: matplotlib
Requires-Dist: numpy
Requires-Dist: oemof.network==0.5.0a1
Requires-Dist: oemof.solph==0.5.0
Requires-Dist: oemof.thermal==0.0.6
Requires-Dist: oemof.tools==0.4.2
Requires-Dist: openpyxl
Requires-Dist: pandas
Requires-Dist: pandas-stubs
Requires-Dist: plotly
Requires-Dist: pvlib
Requires-Dist: Pyomo
Requires-Dist: recommonmark
Requires-Dist: scipy
Requires-Dist: workalendar
Requires-Dist: xlrd
Requires-Dist: xlwt
Requires-Dist: dash
Requires-Dist: dash-core-components
Requires-Dist: dash_cytoscape
Requires-Dist: dash-html-components
Requires-Dist: dash-table
Dynamic: author
Dynamic: author-email
Dynamic: classifier
Dynamic: description
Dynamic: description-content-type
Dynamic: home-page
Dynamic: license-file
Dynamic: requires-dist
Dynamic: requires-python
Dynamic: summary
